Workbook

Sheet Henrico_Invest
A1: HENRICO INVEST | SIMULADOR INTELIGENTE DE FUNDOS IMOBILIÁRIOS
A2: Ferramenta de Projeção Patrimonial, Renda Passiva Mensal e Alocação Estratégica por Perfil de Investidor
A4: PATRIMÔNIO ACUMULADO | C4: DIVIDENDO MENSAL ESTIMADO | E4: SUGESTÃO DE APORTE (30%) | G4: PERFIL SELECIONADO
A5: =C17 -> 16755.383 | C5: =C18 -> 100.5323 | E5: =sugestao_investimento -> 600 | G5: =C29 -> Moderado
A6: Prazo Selecionado | C6: Renda Passiva Mensal | E6: Base: Salário Informado | G6: Alocação Estratégica Ativa
A8: 1. CONFIGURAÇÕES BASE | F8: DISTRIBUIÇÃO POR TIPO DE FII
A9: Salário Mensal do Investidor | C9: 2000
A10: Rendimento Mensal da Carteira (Yield) | C10: 0.006
A11: Sugestão de Aporte (30% do Salário) | C11: =salario*0.3 -> 600
A13: 2. INVESTIMENTO MENSAL & RETORNO (5 PERGUNTAS)
A14: 1. Quanto investir por mês? (Aporte) | C14: 200
A15: 2. Por quantos anos investir? (Prazo) | C15: 5
A16: 3. Qual a taxa de rendimento mensal? (Total) | C16: 0.01079
A17: 4. Quanto de patrimônio vai acumular? (Total) | C17: =FV(taxa_mensal,qtd_anos*12,-aporte,0,0) -> 16755.383
A18: 5. Quanto vai receber de dividendos por mês? | C18: =patrimonio*rendimento_carteira -> 100.5323
A20: 3. CENÁRIOS DE PROJEÇÃO DE LONGO PRAZO | F20: EVOLUÇÃO DO PATRIMÔNIO NO TEMPO
A21: Prazo (Anos) | B21: Cenário de Tempo | C21: Patrimônio Acumulado | D21: Dividendo Mensal
A22: 2 | B22: Projeção em 2 Anos | C22: =FV($C$16,$A22*12,-$C$14,0,0) -> 5445.5255 | D22: =C22*rendimento_carteira -> 32.673153
A23: 5 | B23: Projeção em 5 Anos | C23: =FV($C$16,$A23*12,-$C$14,0,0) -> 16755.383 | D23: =C23*rendimento_carteira -> 100.5323
A24: 10 | B24: Projeção em 10 Anos | C24: =FV($C$16,$A24*12,-$C$14,0,0) -> 48656.843 | D24: =C24*rendimento_carteira -> 291.94106
A25: 20 | B25: Projeção em 20 Anos | C25: =FV($C$16,$A25*12,-$C$14,0,0) -> 225039.68 | D25: =C25*rendimento_carteira -> 1350.2381
A26: 30 | B26: Projeção em 30 Anos | C26: =FV($C$16,$A26*12,-$C$14,0,0) -> 864433.93 | D26: =C26*rendimento_carteira -> 5186.6036
A28: 4. ALOCAÇÃO ESTRATÉGICA POR PERFIL DE INVESTIDOR
A29: Perfil de Investidor Selecionado | C29: Moderado
A30: Valor Total do Aporte Mensal | C30: =aporte -> 200
A31: Tipo de FII | B31: Segmento / Racional | C31: Percentual (%) | D31: Valor Alocado (R$)
A32: PAPEL | B32: Títulos de Dívida / CRIs | C32: =VLOOKUP($C$29&"-"&A32,Apoio_Dados!$A$2:$E$19,4,FALSE()) -> 0.32 | D32: =C32*$C$30 -> 64
A33: TIJOLO | B33: Imóveis Físicos / Renda | C33: =VLOOKUP($C$29&"-"&A33,Apoio_Dados!$A$2:$E$19,4,FALSE()) -> 0.35 | D33: =C33*$C$30 -> 70
A34: HÍBRIDOS | B34: Multiestratégia / Misto | C34: =VLOOKUP($C$29&"-"&A34,Apoio_Dados!$A$2:$E$19,4,FALSE()) -> 0.08 | D34: =C34*$C$30 -> 16 | F34: LEGENDA & GUIA DE USO
A35: FOFs | B35: Fundos de Fundos Imobiliários | C35: =VLOOKUP($C$29&"-"&A35,Apoio_Dados!$A$2:$E$19,4,FALSE()) -> 0.05 | D35: =C35*$C$30 -> 10 | F35: 🟦 Células Azuis Claras: Campos editáveis pelo investidor (Aporte, Prazo, Salário, Perfil).
A36: DESENVOLVIMENTO | B36: Obras / Incorporação | C36: =VLOOKUP($C$29&"-"&A36,Apoio_Dados!$A$2:$E$19,4,FALSE()) -> 0.1 | D36: =C36*$C$30 -> 20 | F36: ⬜ Células Cinzas: Fórmulas automáticas protegidas (VF, PROCV, Dividendos, Totais).
A37: HOTELARIAS | B37: Hotelaria / Hospitalidade | C37: =VLOOKUP($C$29&"-"&A37,Apoio_Dados!$A$2:$E$19,4,FALSE()) -> 0.1 | D37: =C37*$C$30 -> 20 | F37: 💡 Dica: Altere o Perfil na célula C29 para ver o gráfico e a tabela mudarem automaticamente!
A38: Total da Carteira | B38: Alocação 100% | C38: =SUM(C32:C37) -> 1 | D38: =SUM(D32:D37) -> 200

Sheet Apoio_Dados
A1: CHAVE | B1: PERFIL | C1: TIPO DE FII | D1: PERCENTUAL | E1: DESCRICAO | G1: LISTA DE PERFIS
A2: Conservador-PAPEL | B2: Conservador | C2: PAPEL | D2: 0.3 | E2: Títulos de dívida e CRIs de alta liquidez | G2: Conservador
A3: Conservador-TIJOLO | B3: Conservador | C3: TIJOLO | D3: 0.5 | E3: Imóveis físicos consolidados (logística/lajes AAA) | G3: Moderado
A4: Conservador-HÍBRIDOS | B4: Conservador | C4: HÍBRIDOS | D4: 0.1 | E4: Carteira mista equilibrada | G4: Agressivo
A5: Conservador-FOFs | B5: Conservador | C5: FOFs | D5: 0.1 | E5: Fundos de fundos com gestão profissional
A6: Conservador-DESENVOLVIMENTO | B6: Conservador | C6: DESENVOLVIMENTO | D6: 0 | E6: Sem exposição a risco de obras
A7: Conservador-HOTELARIAS | B7: Conservador | C7: HOTELARIAS | D7: 0 | E7: Sem exposição a hotelaria
A8: Moderado-PAPEL | B8: Moderado | C8: PAPEL | D8: 0.32 | E8: Equilíbrio entre crédito e imóveis reais
A9: Moderado-TIJOLO | B9: Moderado | C9: TIJOLO | D9: 0.35 | E9: Base sólida de tijolo para renda passiva
A10: Moderado-HÍBRIDOS | B10: Moderado | C10: HÍBRIDOS | D10: 0.08 | E10: Flexibilidade tática multigestão
A11: Moderado-FOFs | B11: Moderado | C11: FOFs | D11: 0.05 | E11: Cotas diversificadas com desconto de mercado
A12: Moderado-DESENVOLVIMENTO | B12: Moderado | C12: DESENVOLVIMENTO | D12: 0.1 | E12: Busca de valorização com novos projetos
A13: Moderado-HOTELARIAS | B13: Moderado | C13: HOTELARIAS | D13: 0.1 | E13: Exposição ao setor de hospitalidade e lazer
A14: Agressivo-PAPEL | B14: Agressivo | C14: PAPEL | D14: 0.5 | E14: Foco em High Yield e retorno acelerado
A15: Agressivo-TIJOLO | B15: Agressivo | C15: TIJOLO | D15: 0.1 | E15: Alocação mínima em tijolo defensivo
A16: Agressivo-HÍBRIDOS | B16: Agressivo | C16: HÍBRIDOS | D16: 0.05 | E16: Posições táticas oportunistas
... A19: Agressivo-HOTELARIAS | B19: Agressivo | C19: HOTELARIAS | D19: 0.1 | E19: Operações estruturadas de nicho
